{
  "sections": {
    "main": {
      "type": "main-product",
      "blocks": {
        "description": {
          "type": "description",
          "settings": {
            "is_tab": false
          }
        },
        "d24a80da-9a82-4a64-ad4c-73aef4e07900": {
          "type": "custom",
          "settings": {
            "code": "{{product.metafields.my_fields.features}}"
          }
        },
        "separator": {
          "type": "separator",
          "settings": {
          }
        },
        "7d5ba1dd-b1b6-490b-8f6c-d48dcd9fca53": {
          "type": "tab",
          "disabled": true,
          "settings": {
            "title": "Description",
            "content": "",
            "custom_liquid": "{{product.description}}",
            "page": ""
          }
        },
        "variant_picker": {
          "type": "variant_picker",
          "disabled": true,
          "settings": {
            "variant_labels": true,
            "picker_type": "button",
            "color_swatches": true
          }
        },
        "4bc503dd-43bf-43f8-bef9-98c9fb560ed8": {
          "type": "quantity_selector",
          "disabled": true,
          "settings": {
          }
        },
        "price": {
          "type": "price",
          "settings": {
          }
        },
        "buy_buttons": {
          "type": "buy_buttons",
          "settings": {
            "show_dynamic_checkout": true,
            "surface_pickup_enable": true
          }
        },
        "3aed184a-5ec4-447b-acf4-3aa11c27a1bd": {
          "type": "product_downloads",
          "disabled": true,
          "settings": {
            "enable_specification_sheet": true,
            "enable_user_manual": true
          }
        }
      },
      "block_order": [
        "description",
        "d24a80da-9a82-4a64-ad4c-73aef4e07900",
        "separator",
        "7d5ba1dd-b1b6-490b-8f6c-d48dcd9fca53",
        "variant_picker",
        "4bc503dd-43bf-43f8-bef9-98c9fb560ed8",
        "price",
        "buy_buttons",
        "3aed184a-5ec4-447b-acf4-3aa11c27a1bd"
      ],
      "settings": {
        "sku_enable": true,
        "image_size": "medium",
        "product_zoom_enable": true,
        "thumbnail_position": "beside",
        "thumbnail_arrows": true,
        "enable_video_looping": true,
        "product_video_style": "muted"
      }
    },
    "165715069135e58c2b": {
      "type": "manual-buttons",
      "blocks": {
        "21135404-5238-4796-993c-a194918f70bc": {
          "type": "first-section",
          "settings": {
            "view-btn": ""
          }
        }
      },
      "block_order": [
        "21135404-5238-4796-993c-a194918f70bc"
      ],
      "settings": {
      }
    },
    "sub": {
      "type": "product-full-width",
      "disabled": true,
      "settings": {
        "max_width": true
      }
    },
    "1655372404eeb81c88": {
      "type": "metafield-content",
      "disabled": true,
      "blocks": {
        "eb3ea5d7-216c-46ce-9990-1260ed53bc99": {
          "type": "overview",
          "settings": {
            "name": "Overview"
          }
        },
        "d1ec4bb4-55d0-48f9-b0cd-bbe2766b8bb5": {
          "type": "benefits",
          "settings": {
            "name": "Benefits"
          }
        },
        "419869fd-ed12-4cc3-8915-e64cfd83f8b3": {
          "type": "keyfeatures",
          "settings": {
            "name": "Key features"
          }
        },
        "2b9ec5d7-5b8a-462e-9bca-2646f8543921": {
          "type": "specifications",
          "settings": {
            "name": "Specifications"
          }
        },
        "a5d28bcb-e528-4d1f-aea2-5c8324d7536c": {
          "type": "user_manual",
          "settings": {
            "name": "User manual & Downloads"
          }
        },
        "285a322d-9d15-4dd2-881b-9dae307f19de": {
          "type": "product-recommendations",
          "settings": {
            "show_product_recommendations": true,
            "product_recommendations_heading": "Related products",
            "related_count": 5
          }
        }
      },
      "block_order": [
        "eb3ea5d7-216c-46ce-9990-1260ed53bc99",
        "d1ec4bb4-55d0-48f9-b0cd-bbe2766b8bb5",
        "419869fd-ed12-4cc3-8915-e64cfd83f8b3",
        "2b9ec5d7-5b8a-462e-9bca-2646f8543921",
        "a5d28bcb-e528-4d1f-aea2-5c8324d7536c",
        "285a322d-9d15-4dd2-881b-9dae307f19de"
      ],
      "settings": {
        "btn_text": "",
        "link": "shopify:\/\/pages\/store-locator"
      }
    },
    "165544510106ce9654": {
      "type": "apps",
      "disabled": true,
      "blocks": {
        "7e7780ef-d7a3-4331-aee3-d4faf2743019": {
          "type": "shopify:\/\/apps\/product-reviews\/blocks\/reviews\/bae150af-8da8-48b2-9867-398188115e5f",
          "disabled": true,
          "settings": {
          }
        }
      },
      "block_order": [
        "7e7780ef-d7a3-4331-aee3-d4faf2743019"
      ],
      "settings": {
        "full_width": false,
        "space_around": true
      }
    },
    "product-recommendations": {
      "type": "product-recommendations",
      "disabled": true,
      "settings": {
        "show_product_recommendations": true,
        "product_recommendations_heading": "You may also like",
        "related_count": 5
      }
    },
    "collection-return": {
      "type": "collection-return",
      "disabled": true,
      "settings": {
      }
    },
    "1657150753ebe8393d": {
      "type": "contact-form",
      "disabled": true,
      "settings": {
        "title": "Ask for more info about this product",
        "text": "",
        "show_phone": false,
        "narrow_column": false
      }
    }
  },
  "order": [
    "main",
    "165715069135e58c2b",
    "sub",
    "1655372404eeb81c88",
    "165544510106ce9654",
    "product-recommendations",
    "collection-return",
    "1657150753ebe8393d"
  ]
}